synthetic_gravity_waves/__init__.py
synthetic_gravity_waves/components.py
synthetic_gravity_waves/composite.py
synthetic_gravity_waves/point_sampling.py
synthetic_gravity_waves-0.1.2.dist-info/LICENSE
synthetic_gravity_waves-0.1.2.dist-info/METADATA
synthetic_gravity_waves-0.1.2.dist-info/WHEEL
synthetic_gravity_waves-0.1.2.dist-info/top_level.txt
synthetic_gravity_waves-0.1.2.dist-info/RECORD
