Metadata-Version: 2.1
Name: synthetic-gravity-waves
Version: 0.1.2
Summary: Python package for generation of synthetic gravity waves
Home-page: https://github.com/leifdenby/synthetic-gravity-waves
Author: Leif Denby
Author-email: leif@denby.eu
License-File: LICENSE
Requires-Dist: scipy
Requires-Dist: numpy
Provides-Extra: dev
Requires-Dist: pytest ; extra == 'dev'
Requires-Dist: nbval ; extra == 'dev'
Requires-Dist: nb-black ; extra == 'dev'
Requires-Dist: matplotlib ; extra == 'dev'
Requires-Dist: pre-commit ; extra == 'dev'
Requires-Dist: ipython ; extra == 'dev'
Provides-Extra: lint
Requires-Dist: pre-commit ; extra == 'lint'
Provides-Extra: test
Requires-Dist: pytest ; extra == 'test'
Requires-Dist: nbval ; extra == 'test'
Requires-Dist: nb-black ; extra == 'test'
Requires-Dist: matplotlib ; extra == 'test'
